django_route_mapper/__init__.py
django_route_mapper-0.1.0.dist-info/licenses/LICENSE
django_route_mapper-0.1.0.dist-info/METADATA
django_route_mapper-0.1.0.dist-info/WHEEL
django_route_mapper-0.1.0.dist-info/top_level.txt
django_route_mapper-0.1.0.dist-info/RECORD
